spectoml/__init__.py
spectoml/_util.py
spectoml/base.py
spectoml/callable.py
spectoml/errors.py
spectoml/keyed.py
spectoml/py.typed
spectoml/source.py
spectoml/value.py
spectoml/specs/__init__.py
spectoml/specs/arrays.py
spectoml/specs/tables.py
spectoml/specs/values.py
spectoml-0.1.0.dist-info/METADATA
spectoml-0.1.0.dist-info/WHEEL
spectoml-0.1.0.dist-info/licenses/COPYING.md
spectoml-0.1.0.dist-info/RECORD
